nonebot_plugin_repeater/__init__.py
nonebot_plugin_repeater/config.py
nonebot_plugin_repeater-3.1.4.dist-info/LICENSE
nonebot_plugin_repeater-3.1.4.dist-info/METADATA
nonebot_plugin_repeater-3.1.4.dist-info/WHEEL
nonebot_plugin_repeater-3.1.4.dist-info/top_level.txt
nonebot_plugin_repeater-3.1.4.dist-info/RECORD
