Metadata-Version: 2.1
Name: nonebot-plugin-repeater
Version: 3.1.4
Summary: A plugin based on NoneBot2, auto +1 in group.
Home-page: https://github.com/ninthseason/nonebot-plugin-repeater
Author: Kl1nge5
Project-URL: Bug Tracker, https://github.com/ninthseason/nonebot-plugin-repeater/issues
Classifier: Programming Language :: Python :: 3
Classifier: License :: OSI Approved :: GNU General Public License v3 (GPLv3)
Classifier: Operating System :: OS Independent
Requires-Python: >=3.7
License-File: LICENSE
